fastapi_starter_template/__init__.py
fastapi_starter_template/cli.py
fastapi_starter_template-0.1.2.dist-info/METADATA
fastapi_starter_template-0.1.2.dist-info/WHEEL
fastapi_starter_template-0.1.2.dist-info/entry_points.txt
fastapi_starter_template-0.1.2.dist-info/RECORD
