Metadata-Version: 2.1
Name: fastapi-starter-template
Version: 0.1.2
Summary: Um template para iniciar projetos FastAPI rapidamente
Author: Kaue Curti
Author-email: kauecurti@hotmail.com
Requires-Python: >=3.9,<4.0
Classifier: Programming Language :: Python :: 3
Classifier: Programming Language :: Python :: 3.9
Classifier: Programming Language :: Python :: 3.10
Classifier: Programming Language :: Python :: 3.11
Classifier: Programming Language :: Python :: 3.12
Requires-Dist: click (>=8.1.7,<9.0.0)
Requires-Dist: fastapi (>=0.110.0,<0.111.0)
Requires-Dist: pydantic (>=2.6.4,<3.0.0)
Requires-Dist: uvicorn (>=0.29.0,<0.30.0)
